atomicpuppy_sqlcounter.py
atomicpuppy_sqlcounter-0.21.dist-info/METADATA
atomicpuppy_sqlcounter-0.21.dist-info/RECORD
atomicpuppy_sqlcounter-0.21.dist-info/WHEEL
atomicpuppy_sqlcounter-0.21.dist-info/top_level.txt
